front11_plus/__init__.py
front11_plus/front11_plus.py
Front11_plus-0.1.4.dist-info/METADATA
Front11_plus-0.1.4.dist-info/WHEEL
Front11_plus-0.1.4.dist-info/top_level.txt
Front11_plus-0.1.4.dist-info/RECORD
