Metadata-Version: 2.1
Name: Front11_plus
Version: 0.1.4
Summary: Default template for PDM package
Author-email: minju210 <juliana6190210@gmail.com>
License: MIT
Requires-Python: >=3.9
